mujoco_viz/__init__.py
mujoco_viz/mujoco_viz.cpython-310-aarch64-linux-gnu.so
mujoco_viz/mujoco_viz.cpython-310-x86_64-linux-gnu.so
mujoco_viz-0.0.3.dist-info/METADATA
mujoco_viz-0.0.3.dist-info/WHEEL
mujoco_viz-0.0.3.dist-info/top_level.txt
mujoco_viz-0.0.3.dist-info/RECORD
